KevinKPytrends/__init__.py
KevinKPytrends/dailydata.py
KevinKPytrends/exceptions.py
KevinKPytrends/request.py
KevinKPytrends/test_trendReq.py
KevinKPytrends-0.1.dist-info/METADATA
KevinKPytrends-0.1.dist-info/WHEEL
KevinKPytrends-0.1.dist-info/top_level.txt
KevinKPytrends-0.1.dist-info/RECORD
